x/__init__.py
x/_ver.py
xlibs-0.0.5.dist-info/METADATA
xlibs-0.0.5.dist-info/WHEEL
xlibs-0.0.5.dist-info/top_level.txt
xlibs-0.0.5.dist-info/RECORD
