Metadata-Version: 2.1
Name: xlibs
Version: 0.0.5
Summary: UNKNOWN
License: UNKNOWN
Platform: UNKNOWN
Requires-Python: >=3.8
Requires-Dist: pandas
Requires-Dist: numpy
Requires-Dist: pyarrow
Requires-Dist: thelogger
Requires-Dist: icecream
Requires-Dist: importlib-metadata (>=1.0) ; python_version < "3.8"
